dicom_sequence_classifier/__init__.py
dicom_sequence_classifier/Model/DICOMMetaData.py
dicom_sequence_classifier/Model/__init__.py
dicom_sequence_classifier/Services/DICOMCheckers.py
dicom_sequence_classifier/Services/DICOMReader.py
dicom_sequence_classifier/Services/__init__.py
dicom_sequence_classifier-1.0.4.dist-info/licenses/LICENSE
dicom_sequence_classifier-1.0.4.dist-info/METADATA
dicom_sequence_classifier-1.0.4.dist-info/WHEEL
dicom_sequence_classifier-1.0.4.dist-info/top_level.txt
dicom_sequence_classifier-1.0.4.dist-info/RECORD
