Metadata-Version: 2.4
Name: dicom-sequence-classifier
Version: 1.0.4
Summary: Python package based on Pydicom that scans, analyzes and try to classifies DICOM sequences by type
Home-page: https://github.com/LICE-dev/dicom_sequence_classifier
Author: LICE - Commissione Neuroimmagini
Author-email: dev@lice.it
License: MIT
Classifier: Programming Language :: Python :: 3
Classifier: License :: OSI Approved :: MIT License
Classifier: Operating System :: OS Independent
Requires-Python: >=3.7
License-File: LICENSE
Requires-Dist: pydicom>=3.0.0
Dynamic: author
Dynamic: author-email
Dynamic: classifier
Dynamic: home-page
Dynamic: license
Dynamic: license-file
Dynamic: requires-dist
Dynamic: requires-python
Dynamic: summary
